datavents/__init__.py
datavents/client.py
datavents/normalize.py
datavents/schemas.py
datavents/vendors.py
datavents/ws.py
datavents/providers/__init__.py
datavents/providers/config.py
datavents/providers/kalshi/__init__.py
datavents/providers/kalshi/base_client.py
datavents/providers/kalshi/kalshi_rest_auth.py
datavents/providers/kalshi/kalshi_rest_noauth.py
datavents/providers/kalshi/rest_auth.py
datavents/providers/kalshi/ws_client.py
datavents/providers/polymarket/__init__.py
datavents/providers/polymarket/base_client.py
datavents/providers/polymarket/polymarket_rest_noauth.py
datavents/providers/polymarket/rest_auth.py
datavents/providers/polymarket/ws_client.py
datavents/providers/shared_connection/__init__.py
datavents/providers/shared_connection/base_client.py
datavents/providers/shared_connection/rate_limit.py
datavents/providers/shared_connection/rest_client.py
datavents/providers/shared_connection/ws_client.py
datavents/utils/enums.py
datavents/utils/params.py
datavents/utils/resolve.py
datavents/utils/vendors.py
datavents/utils/ws.py
datavents-0.1.1.dist-info/METADATA
datavents-0.1.1.dist-info/WHEEL
datavents-0.1.1.dist-info/licenses/LICENSE
datavents-0.1.1.dist-info/RECORD
