Metadata-Version: 2.4
Name: datavents
Version: 0.1.1
Summary: DataVents Open SDK: unified clients and normalization for Kalshi & Polymarket
Project-URL: Homepage, https://github.com/ajclemendor/DataVentsOpen
Project-URL: Repository, https://github.com/ajclemendor/DataVentsOpen.git
Project-URL: Issues, https://github.com/ajclemendor/DataVentsOpen/issues
Author-email: AJ Clemendor <ajclemendor@gmail.com>
License: MIT
License-File: LICENSE
Requires-Python: >=3.9
Requires-Dist: certifi>=2024.2.2
Requires-Dist: cryptography>=42
Requires-Dist: eth-account>=0.11
Requires-Dist: overrides>=7
Requires-Dist: pydantic>=2.3
Requires-Dist: python-dotenv>=1
Requires-Dist: requests>=2.31
Requires-Dist: websockets>=12
Provides-Extra: dev
Requires-Dist: pytest>=8; extra == 'dev'
Requires-Dist: ruff>=0.6; extra == 'dev'
